loadero_python/__init__.py
loadero_python/api_client.py
loadero_python/resources/__init__.py
loadero_python/resources/assert_precondition.py
loadero_python/resources/assert_resource.py
loadero_python/resources/classificator.py
loadero_python/resources/file.py
loadero_python/resources/group.py
loadero_python/resources/metric_path.py
loadero_python/resources/pagination.py
loadero_python/resources/participant.py
loadero_python/resources/project.py
loadero_python/resources/resource.py
loadero_python/resources/result.py
loadero_python/resources/run.py
loadero_python/resources/run_participant.py
loadero_python/resources/test.py
loadero_python-1.3.0.dist-info/LICENSE.md
loadero_python-1.3.0.dist-info/METADATA
loadero_python-1.3.0.dist-info/WHEEL
loadero_python-1.3.0.dist-info/top_level.txt
loadero_python-1.3.0.dist-info/RECORD
