Metadata-Version: 2.1
Name: loadero_python
Version: 1.3.0
Summary: Python client for Loadero API
Home-page: https://github.com/loadero/loadero-python
Author: Loadero Team
Author-email: support@loadero.com
License: GPLv3
Project-URL: Documentation, https://loadero.github.io/loadero-python/
Project-URL: Source, https://github.com/loadero/loadero-python
Project-URL: Tracker, https://github.com/loadero/loadero-python/issues
Project-URL: Loadero, https://loadero.com/
Keywords: loadero
Classifier: Development Status :: 5 - Production/Stable
Classifier: Intended Audience :: Developers
Classifier: Topic :: Software Development :: Quality Assurance
Classifier: License :: OSI Approved :: GNU General Public License v3 (GPLv3)
Classifier: Programming Language :: Python :: 3.7
Classifier: Programming Language :: Python :: 3.8
Classifier: Programming Language :: Python :: 3.9
Classifier: Programming Language :: Python :: 3.10
Classifier: Programming Language :: Python :: 3.11
Requires-Python: >=3.9, <4
License-File: LICENSE.md
Requires-Dist: urllib3==1.26.19
Requires-Dist: python-dateutil==2.8.2
